{
    "Entries": [
        {
            "facing": "north",
            "roadStartPosition": [7, -1, -1],
            "type": "mainEntry"
        }
    ],
    "Size": [16, 14, 15],
    "Offsets": [4, 0, 0],
    "Type": 1,
    "Level": 2,
    "RequiredResource": {
        "human": 0,
        "wood": 800,
        "stone": 350,
        "food": 0,
        "ironOre": 300,
        "iron": 0,
        "grass": 0
    },
    "ProduceResource": {
        "human": 0,
        "wood": 500,
        "stone": 0,
        "food": 0,
        "ironOre": 0,
        "iron": 40,
        "grass": 0
    }
}
